[{"s":7,"a":74,"wi":1,"t":"وَٱذْكُرُوٓا۟","n":"واذكروا"},{"s":7,"a":74,"wi":2,"t":"إِذْ","n":"اذ"},{"s":7,"a":74,"wi":3,"t":"جَعَلَكُمْ","n":"جعلكم"},{"s":7,"a":74,"wi":4,"t":"خُلَفَآءَ","n":"خلفاء"},{"s":7,"a":74,"wi":5,"t":"مِنۢ","n":"من"},{"s":7,"a":74,"wi":6,"t":"بَعْدِ","n":"بعد"},{"s":7,"a":74,"wi":7,"t":"عَادٍۢ","n":"عاد"},{"s":7,"a":74,"wi":8,"t":"وَبَوَّأَكُمْ","n":"وبواكم"},{"s":7,"a":74,"wi":9,"t":"فِى","n":"في"},{"s":7,"a":74,"wi":10,"t":"ٱلْأَرْضِ","n":"الارض"},{"s":7,"a":74,"wi":11,"t":"تَتَّخِذُونَ","n":"تتخذون"},{"s":7,"a":74,"wi":12,"t":"مِن","n":"من"},{"s":7,"a":74,"wi":13,"t":"سُهُولِهَا","n":"سهولها"},{"s":7,"a":74,"wi":14,"t":"قُصُورًۭا","n":"قصورا"},{"s":7,"a":74,"wi":15,"t":"وَتَنْحِتُونَ","n":"وتنحتون"},{"s":7,"a":74,"wi":16,"t":"ٱلْجِبَالَ","n":"الجبال"},{"s":7,"a":74,"wi":17,"t":"بُيُوتًۭا ۖ","n":"بيوتا"},{"s":7,"a":74,"wi":18,"t":"فَٱذْكُرُوٓا۟","n":"فاذكروا"},{"s":7,"a":74,"wi":19,"t":"ءَالَآءَ","n":"ءالاء"},{"s":7,"a":74,"wi":20,"t":"ٱللَّهِ","n":"الله"},{"s":7,"a":74,"wi":21,"t":"وَلَا","n":"ولا"},{"s":7,"a":74,"wi":22,"t":"تَعْثَوْا۟","n":"تعثوا"},{"s":7,"a":74,"wi":23,"t":"فِى","n":"في"},{"s":7,"a":74,"wi":24,"t":"ٱلْأَرْضِ","n":"الارض"},{"s":7,"a":74,"wi":25,"t":"مُفْسِدِينَ","n":"مفسدين"},{"s":7,"a":75,"wi":1,"t":"قَالَ","n":"قال"},{"s":7,"a":75,"wi":2,"t":"ٱلْمَلَأُ","n":"الملا"},{"s":7,"a":75,"wi":3,"t":"ٱلَّذِينَ","n":"الذين"},{"s":7,"a":75,"wi":4,"t":"ٱسْتَكْبَرُوا۟","n":"استكبروا"},{"s":7,"a":75,"wi":5,"t":"مِن","n":"من"},{"s":7,"a":75,"wi":6,"t":"قَوْمِهِۦ","n":"قومه"},{"s":7,"a":75,"wi":7,"t":"لِلَّذِينَ","n":"للذين"},{"s":7,"a":75,"wi":8,"t":"ٱسْتُضْعِفُوا۟","n":"استضعفوا"},{"s":7,"a":75,"wi":9,"t":"لِمَنْ","n":"لمن"},{"s":7,"a":75,"wi":10,"t":"ءَامَنَ","n":"ءامن"},{"s":7,"a":75,"wi":11,"t":"مِنْهُمْ","n":"منهم"},{"s":7,"a":75,"wi":12,"t":"أَتَعْلَمُونَ","n":"اتعلمون"},{"s":7,"a":75,"wi":13,"t":"أَنَّ","n":"ان"},{"s":7,"a":75,"wi":14,"t":"صَـٰلِحًۭا","n":"صـلحا"},{"s":7,"a":75,"wi":15,"t":"مُّرْسَلٌۭ","n":"مرسل"},{"s":7,"a":75,"wi":16,"t":"مِّن","n":"من"},{"s":7,"a":75,"wi":17,"t":"رَّبِّهِۦ ۚ","n":"ربه"},{"s":7,"a":75,"wi":18,"t":"قَالُوٓا۟","n":"قالوا"},{"s":7,"a":75,"wi":19,"t":"إِنَّا","n":"انا"},{"s":7,"a":75,"wi":20,"t":"بِمَآ","n":"بما"},{"s":7,"a":75,"wi":21,"t":"أُرْسِلَ","n":"ارسل"},{"s":7,"a":75,"wi":22,"t":"بِهِۦ","n":"به"},{"s":7,"a":75,"wi":23,"t":"مُؤْمِنُونَ","n":"مومنون"},{"s":7,"a":76,"wi":1,"t":"قَالَ","n":"قال"},{"s":7,"a":76,"wi":2,"t":"ٱلَّذِينَ","n":"الذين"},{"s":7,"a":76,"wi":3,"t":"ٱسْتَكْبَرُوٓا۟","n":"استكبروا"},{"s":7,"a":76,"wi":4,"t":"إِنَّا","n":"انا"},{"s":7,"a":76,"wi":5,"t":"بِٱلَّذِىٓ","n":"بالذي"},{"s":7,"a":76,"wi":6,"t":"ءَامَنتُم","n":"ءامنتم"},{"s":7,"a":76,"wi":7,"t":"بِهِۦ","n":"به"},{"s":7,"a":76,"wi":8,"t":"كَـٰفِرُونَ","n":"كـفرون"},{"s":7,"a":77,"wi":1,"t":"فَعَقَرُوا۟","n":"فعقروا"},{"s":7,"a":77,"wi":2,"t":"ٱلنَّاقَةَ","n":"الناقه"},{"s":7,"a":77,"wi":3,"t":"وَعَتَوْا۟","n":"وعتوا"},{"s":7,"a":77,"wi":4,"t":"عَنْ","n":"عن"},{"s":7,"a":77,"wi":5,"t":"أَمْرِ","n":"امر"},{"s":7,"a":77,"wi":6,"t":"رَبِّهِمْ","n":"ربهم"},{"s":7,"a":77,"wi":7,"t":"وَقَالُوا۟","n":"وقالوا"},{"s":7,"a":77,"wi":8,"t":"يَـٰصَـٰلِحُ","n":"يـصـلح"},{"s":7,"a":77,"wi":9,"t":"ٱئْتِنَا","n":"ايتنا"},{"s":7,"a":77,"wi":10,"t":"بِمَا","n":"بما"},{"s":7,"a":77,"wi":11,"t":"تَعِدُنَآ","n":"تعدنا"},{"s":7,"a":77,"wi":12,"t":"إِن","n":"ان"},{"s":7,"a":77,"wi":13,"t":"كُنتَ","n":"كنت"},{"s":7,"a":77,"wi":14,"t":"مِنَ","n":"من"},{"s":7,"a":77,"wi":15,"t":"ٱلْمُرْسَلِينَ","n":"المرسلين"},{"s":7,"a":78,"wi":1,"t":"فَأَخَذَتْهُمُ","n":"فاخذتهم"},{"s":7,"a":78,"wi":2,"t":"ٱلرَّجْفَةُ","n":"الرجفه"},{"s":7,"a":78,"wi":3,"t":"فَأَصْبَحُوا۟","n":"فاصبحوا"},{"s":7,"a":78,"wi":4,"t":"فِى","n":"في"},{"s":7,"a":78,"wi":5,"t":"دَارِهِمْ","n":"دارهم"},{"s":7,"a":78,"wi":6,"t":"جَـٰثِمِينَ","n":"جـثمين"},{"s":7,"a":79,"wi":1,"t":"فَتَوَلَّىٰ","n":"فتولي"},{"s":7,"a":79,"wi":2,"t":"عَنْهُمْ","n":"عنهم"},{"s":7,"a":79,"wi":3,"t":"وَقَالَ","n":"وقال"},{"s":7,"a":79,"wi":4,"t":"يَـٰقَوْمِ","n":"يـقوم"},{"s":7,"a":79,"wi":5,"t":"لَقَدْ","n":"لقد"},{"s":7,"a":79,"wi":6,"t":"أَبْلَغْتُكُمْ","n":"ابلغتكم"},{"s":7,"a":79,"wi":7,"t":"رِسَالَةَ","n":"رساله"},{"s":7,"a":79,"wi":8,"t":"رَبِّى","n":"ربي"},{"s":7,"a":79,"wi":9,"t":"وَنَصَحْتُ","n":"ونصحت"},{"s":7,"a":79,"wi":10,"t":"لَكُمْ","n":"لكم"},{"s":7,"a":79,"wi":11,"t":"وَلَـٰكِن","n":"ولـكن"},{"s":7,"a":79,"wi":12,"t":"لَّا","n":"لا"},{"s":7,"a":79,"wi":13,"t":"تُحِبُّونَ","n":"تحبون"},{"s":7,"a":79,"wi":14,"t":"ٱلنَّـٰصِحِينَ","n":"النـصحين"},{"s":7,"a":80,"wi":1,"t":"وَلُوطًا","n":"ولوطا"},{"s":7,"a":80,"wi":2,"t":"إِذْ","n":"اذ"},{"s":7,"a":80,"wi":3,"t":"قَالَ","n":"قال"},{"s":7,"a":80,"wi":4,"t":"لِقَوْمِهِۦٓ","n":"لقومه"},{"s":7,"a":80,"wi":5,"t":"أَتَأْتُونَ","n":"اتاتون"},{"s":7,"a":80,"wi":6,"t":"ٱلْفَـٰحِشَةَ","n":"الفـحشه"},{"s":7,"a":80,"wi":7,"t":"مَا","n":"ما"},{"s":7,"a":80,"wi":8,"t":"سَبَقَكُم","n":"سبقكم"},{"s":7,"a":80,"wi":9,"t":"بِهَا","n":"بها"},{"s":7,"a":80,"wi":10,"t":"مِنْ","n":"من"},{"s":7,"a":80,"wi":11,"t":"أَحَدٍۢ","n":"احد"},{"s":7,"a":80,"wi":12,"t":"مِّنَ","n":"من"},{"s":7,"a":80,"wi":13,"t":"ٱلْعَـٰلَمِينَ","n":"العـلمين"},{"s":7,"a":81,"wi":1,"t":"إِنَّكُمْ","n":"انكم"},{"s":7,"a":81,"wi":2,"t":"لَتَأْتُونَ","n":"لتاتون"},{"s":7,"a":81,"wi":3,"t":"ٱلرِّجَالَ","n":"الرجال"},{"s":7,"a":81,"wi":4,"t":"شَهْوَةًۭ","n":"شهوه"},{"s":7,"a":81,"wi":5,"t":"مِّن","n":"من"},{"s":7,"a":81,"wi":6,"t":"دُونِ","n":"دون"},{"s":7,"a":81,"wi":7,"t":"ٱلنِّسَآءِ ۚ","n":"النساء"},{"s":7,"a":81,"wi":8,"t":"بَلْ","n":"بل"},{"s":7,"a":81,"wi":9,"t":"أَنتُمْ","n":"انتم"},{"s":7,"a":81,"wi":10,"t":"قَوْمٌۭ","n":"قوم"},{"s":7,"a":81,"wi":11,"t":"مُّسْرِفُونَ","n":"مسرفون"}]