[{"s":8,"a":46,"wi":1,"t":"وَأَطِيعُوا۟","n":"واطيعوا"},{"s":8,"a":46,"wi":2,"t":"ٱللَّهَ","n":"الله"},{"s":8,"a":46,"wi":3,"t":"وَرَسُولَهُۥ","n":"ورسوله"},{"s":8,"a":46,"wi":4,"t":"وَلَا","n":"ولا"},{"s":8,"a":46,"wi":5,"t":"تَنَـٰزَعُوا۟","n":"تنـزعوا"},{"s":8,"a":46,"wi":6,"t":"فَتَفْشَلُوا۟","n":"فتفشلوا"},{"s":8,"a":46,"wi":7,"t":"وَتَذْهَبَ","n":"وتذهب"},{"s":8,"a":46,"wi":8,"t":"رِيحُكُمْ ۖ","n":"ريحكم"},{"s":8,"a":46,"wi":9,"t":"وَٱصْبِرُوٓا۟ ۚ","n":"واصبروا"},{"s":8,"a":46,"wi":10,"t":"إِنَّ","n":"ان"},{"s":8,"a":46,"wi":11,"t":"ٱللَّهَ","n":"الله"},{"s":8,"a":46,"wi":12,"t":"مَعَ","n":"مع"},{"s":8,"a":46,"wi":13,"t":"ٱلصَّـٰبِرِينَ","n":"الصـبرين"},{"s":8,"a":47,"wi":1,"t":"وَلَا","n":"ولا"},{"s":8,"a":47,"wi":2,"t":"تَكُونُوا۟","n":"تكونوا"},{"s":8,"a":47,"wi":3,"t":"كَٱلَّذِينَ","n":"كالذين"},{"s":8,"a":47,"wi":4,"t":"خَرَجُوا۟","n":"خرجوا"},{"s":8,"a":47,"wi":5,"t":"مِن","n":"من"},{"s":8,"a":47,"wi":6,"t":"دِيَـٰرِهِم","n":"ديـرهم"},{"s":8,"a":47,"wi":7,"t":"بَطَرًۭا","n":"بطرا"},{"s":8,"a":47,"wi":8,"t":"وَرِئَآءَ","n":"ورياء"},{"s":8,"a":47,"wi":9,"t":"ٱلنَّاسِ","n":"الناس"},{"s":8,"a":47,"wi":10,"t":"وَيَصُدُّونَ","n":"ويصدون"},{"s":8,"a":47,"wi":11,"t":"عَن","n":"عن"},{"s":8,"a":47,"wi":12,"t":"سَبِيلِ","n":"سبيل"},{"s":8,"a":47,"wi":13,"t":"ٱللَّهِ ۚ","n":"الله"},{"s":8,"a":47,"wi":14,"t":"وَٱللَّهُ","n":"والله"},{"s":8,"a":47,"wi":15,"t":"بِمَا","n":"بما"},{"s":8,"a":47,"wi":16,"t":"يَعْمَلُونَ","n":"يعملون"},{"s":8,"a":47,"wi":17,"t":"مُحِيطٌۭ","n":"محيط"},{"s":8,"a":48,"wi":1,"t":"وَإِذْ","n":"واذ"},{"s":8,"a":48,"wi":2,"t":"زَيَّنَ","n":"زين"},{"s":8,"a":48,"wi":3,"t":"لَهُمُ","n":"لهم"},{"s":8,"a":48,"wi":4,"t":"ٱلشَّيْطَـٰنُ","n":"الشيطـن"},{"s":8,"a":48,"wi":5,"t":"أَعْمَـٰلَهُمْ","n":"اعمـلهم"},{"s":8,"a":48,"wi":6,"t":"وَقَالَ","n":"وقال"},{"s":8,"a":48,"wi":7,"t":"لَا","n":"لا"},{"s":8,"a":48,"wi":8,"t":"غَالِبَ","n":"غالب"},{"s":8,"a":48,"wi":9,"t":"لَكُمُ","n":"لكم"},{"s":8,"a":48,"wi":10,"t":"ٱلْيَوْمَ","n":"اليوم"},{"s":8,"a":48,"wi":11,"t":"مِنَ","n":"من"},{"s":8,"a":48,"wi":12,"t":"ٱلنَّاسِ","n":"الناس"},{"s":8,"a":48,"wi":13,"t":"وَإِنِّى","n":"واني"},{"s":8,"a":48,"wi":14,"t":"جَارٌۭ","n":"جار"},{"s":8,"a":48,"wi":15,"t":"لَّكُمْ ۖ","n":"لكم"},{"s":8,"a":48,"wi":16,"t":"فَلَمَّا","n":"فلما"},{"s":8,"a":48,"wi":17,"t":"تَرَآءَتِ","n":"تراءت"},{"s":8,"a":48,"wi":18,"t":"ٱلْفِئَتَانِ","n":"الفيتان"},{"s":8,"a":48,"wi":19,"t":"نَكَصَ","n":"نكص"},{"s":8,"a":48,"wi":20,"t":"عَلَىٰ","n":"علي"},{"s":8,"a":48,"wi":21,"t":"عَقِبَيْهِ","n":"عقبيه"},{"s":8,"a":48,"wi":22,"t":"وَقَالَ","n":"وقال"},{"s":8,"a":48,"wi":23,"t":"إِنِّى","n":"اني"},{"s":8,"a":48,"wi":24,"t":"بَرِىٓءٌۭ","n":"بريء"},{"s":8,"a":48,"wi":25,"t":"مِّنكُمْ","n":"منكم"},{"s":8,"a":48,"wi":26,"t":"إِنِّىٓ","n":"اني"},{"s":8,"a":48,"wi":27,"t":"أَرَىٰ","n":"اري"},{"s":8,"a":48,"wi":28,"t":"مَا","n":"ما"},{"s":8,"a":48,"wi":29,"t":"لَا","n":"لا"},{"s":8,"a":48,"wi":30,"t":"تَرَوْنَ","n":"ترون"},{"s":8,"a":48,"wi":31,"t":"إِنِّىٓ","n":"اني"},{"s":8,"a":48,"wi":32,"t":"أَخَافُ","n":"اخاف"},{"s":8,"a":48,"wi":33,"t":"ٱللَّهَ ۚ","n":"الله"},{"s":8,"a":48,"wi":34,"t":"وَٱللَّهُ","n":"والله"},{"s":8,"a":48,"wi":35,"t":"شَدِيدُ","n":"شديد"},{"s":8,"a":48,"wi":36,"t":"ٱلْعِقَابِ","n":"العقاب"},{"s":8,"a":49,"wi":1,"t":"إِذْ","n":"اذ"},{"s":8,"a":49,"wi":2,"t":"يَقُولُ","n":"يقول"},{"s":8,"a":49,"wi":3,"t":"ٱلْمُنَـٰفِقُونَ","n":"المنـفقون"},{"s":8,"a":49,"wi":4,"t":"وَٱلَّذِينَ","n":"والذين"},{"s":8,"a":49,"wi":5,"t":"فِى","n":"في"},{"s":8,"a":49,"wi":6,"t":"قُلُوبِهِم","n":"قلوبهم"},{"s":8,"a":49,"wi":7,"t":"مَّرَضٌ","n":"مرض"},{"s":8,"a":49,"wi":8,"t":"غَرَّ","n":"غر"},{"s":8,"a":49,"wi":9,"t":"هَـٰٓؤُلَآءِ","n":"هـولاء"},{"s":8,"a":49,"wi":10,"t":"دِينُهُمْ ۗ","n":"دينهم"},{"s":8,"a":49,"wi":11,"t":"وَمَن","n":"ومن"},{"s":8,"a":49,"wi":12,"t":"يَتَوَكَّلْ","n":"يتوكل"},{"s":8,"a":49,"wi":13,"t":"عَلَى","n":"علي"},{"s":8,"a":49,"wi":14,"t":"ٱللَّهِ","n":"الله"},{"s":8,"a":49,"wi":15,"t":"فَإِنَّ","n":"فان"},{"s":8,"a":49,"wi":16,"t":"ٱللَّهَ","n":"الله"},{"s":8,"a":49,"wi":17,"t":"عَزِيزٌ","n":"عزيز"},{"s":8,"a":49,"wi":18,"t":"حَكِيمٌۭ","n":"حكيم"},{"s":8,"a":50,"wi":1,"t":"وَلَوْ","n":"ولو"},{"s":8,"a":50,"wi":2,"t":"تَرَىٰٓ","n":"تري"},{"s":8,"a":50,"wi":3,"t":"إِذْ","n":"اذ"},{"s":8,"a":50,"wi":4,"t":"يَتَوَفَّى","n":"يتوفي"},{"s":8,"a":50,"wi":5,"t":"ٱلَّذِينَ","n":"الذين"},{"s":8,"a":50,"wi":6,"t":"كَفَرُوا۟ ۙ","n":"كفروا"},{"s":8,"a":50,"wi":7,"t":"ٱلْمَلَـٰٓئِكَةُ","n":"الملـيكه"},{"s":8,"a":50,"wi":8,"t":"يَضْرِبُونَ","n":"يضربون"},{"s":8,"a":50,"wi":9,"t":"وُجُوهَهُمْ","n":"وجوههم"},{"s":8,"a":50,"wi":10,"t":"وَأَدْبَـٰرَهُمْ","n":"وادبـرهم"},{"s":8,"a":50,"wi":11,"t":"وَذُوقُوا۟","n":"وذوقوا"},{"s":8,"a":50,"wi":12,"t":"عَذَابَ","n":"عذاب"},{"s":8,"a":50,"wi":13,"t":"ٱلْحَرِيقِ","n":"الحريق"},{"s":8,"a":51,"wi":1,"t":"ذَٰلِكَ","n":"ذلك"},{"s":8,"a":51,"wi":2,"t":"بِمَا","n":"بما"},{"s":8,"a":51,"wi":3,"t":"قَدَّمَتْ","n":"قدمت"},{"s":8,"a":51,"wi":4,"t":"أَيْدِيكُمْ","n":"ايديكم"},{"s":8,"a":51,"wi":5,"t":"وَأَنَّ","n":"وان"},{"s":8,"a":51,"wi":6,"t":"ٱللَّهَ","n":"الله"},{"s":8,"a":51,"wi":7,"t":"لَيْسَ","n":"ليس"},{"s":8,"a":51,"wi":8,"t":"بِظَلَّـٰمٍۢ","n":"بظلـم"},{"s":8,"a":51,"wi":9,"t":"لِّلْعَبِيدِ","n":"للعبيد"},{"s":8,"a":52,"wi":1,"t":"كَدَأْبِ","n":"كداب"},{"s":8,"a":52,"wi":2,"t":"ءَالِ","n":"ءال"},{"s":8,"a":52,"wi":3,"t":"فِرْعَوْنَ ۙ","n":"فرعون"},{"s":8,"a":52,"wi":4,"t":"وَٱلَّذِينَ","n":"والذين"},{"s":8,"a":52,"wi":5,"t":"مِن","n":"من"},{"s":8,"a":52,"wi":6,"t":"قَبْلِهِمْ ۚ","n":"قبلهم"},{"s":8,"a":52,"wi":7,"t":"كَفَرُوا۟","n":"كفروا"},{"s":8,"a":52,"wi":8,"t":"بِـَٔايَـٰتِ","n":"بـايـت"},{"s":8,"a":52,"wi":9,"t":"ٱللَّهِ","n":"الله"},{"s":8,"a":52,"wi":10,"t":"فَأَخَذَهُمُ","n":"فاخذهم"},{"s":8,"a":52,"wi":11,"t":"ٱللَّهُ","n":"الله"},{"s":8,"a":52,"wi":12,"t":"بِذُنُوبِهِمْ ۗ","n":"بذنوبهم"},{"s":8,"a":52,"wi":13,"t":"إِنَّ","n":"ان"},{"s":8,"a":52,"wi":14,"t":"ٱللَّهَ","n":"الله"},{"s":8,"a":52,"wi":15,"t":"قَوِىٌّۭ","n":"قوي"},{"s":8,"a":52,"wi":16,"t":"شَدِيدُ","n":"شديد"},{"s":8,"a":52,"wi":17,"t":"ٱلْعِقَابِ","n":"العقاب"}]