[{"s":11,"a":89,"wi":1,"t":"وَيَـٰقَوْمِ","n":"ويـقوم"},{"s":11,"a":89,"wi":2,"t":"لَا","n":"لا"},{"s":11,"a":89,"wi":3,"t":"يَجْرِمَنَّكُمْ","n":"يجرمنكم"},{"s":11,"a":89,"wi":4,"t":"شِقَاقِىٓ","n":"شقاقي"},{"s":11,"a":89,"wi":5,"t":"أَن","n":"ان"},{"s":11,"a":89,"wi":6,"t":"يُصِيبَكُم","n":"يصيبكم"},{"s":11,"a":89,"wi":7,"t":"مِّثْلُ","n":"مثل"},{"s":11,"a":89,"wi":8,"t":"مَآ","n":"ما"},{"s":11,"a":89,"wi":9,"t":"أَصَابَ","n":"اصاب"},{"s":11,"a":89,"wi":10,"t":"قَوْمَ","n":"قوم"},{"s":11,"a":89,"wi":11,"t":"نُوحٍ","n":"نوح"},{"s":11,"a":89,"wi":12,"t":"أَوْ","n":"او"},{"s":11,"a":89,"wi":13,"t":"قَوْمَ","n":"قوم"},{"s":11,"a":89,"wi":14,"t":"هُودٍ","n":"هود"},{"s":11,"a":89,"wi":15,"t":"أَوْ","n":"او"},{"s":11,"a":89,"wi":16,"t":"قَوْمَ","n":"قوم"},{"s":11,"a":89,"wi":17,"t":"صَـٰلِحٍۢ ۚ","n":"صـلح"},{"s":11,"a":89,"wi":18,"t":"وَمَا","n":"وما"},{"s":11,"a":89,"wi":19,"t":"قَوْمُ","n":"قوم"},{"s":11,"a":89,"wi":20,"t":"لُوطٍۢ","n":"لوط"},{"s":11,"a":89,"wi":21,"t":"مِّنكُم","n":"منكم"},{"s":11,"a":89,"wi":22,"t":"بِبَعِيدٍۢ","n":"ببعيد"},{"s":11,"a":90,"wi":1,"t":"وَٱسْتَغْفِرُوا۟","n":"واستغفروا"},{"s":11,"a":90,"wi":2,"t":"رَبَّكُمْ","n":"ربكم"},{"s":11,"a":90,"wi":3,"t":"ثُمَّ","n":"ثم"},{"s":11,"a":90,"wi":4,"t":"تُوبُوٓا۟","n":"توبوا"},{"s":11,"a":90,"wi":5,"t":"إِلَيْهِ ۚ","n":"اليه"},{"s":11,"a":90,"wi":6,"t":"إِنَّ","n":"ان"},{"s":11,"a":90,"wi":7,"t":"رَبِّى","n":"ربي"},{"s":11,"a":90,"wi":8,"t":"رَحِيمٌۭ","n":"رحيم"},{"s":11,"a":90,"wi":9,"t":"وَدُودٌۭ","n":"ودود"},{"s":11,"a":91,"wi":1,"t":"قَالُوا۟","n":"قالوا"},{"s":11,"a":91,"wi":2,"t":"يَـٰشُعَيْبُ","n":"يـشعيب"},{"s":11,"a":91,"wi":3,"t":"مَا","n":"ما"},{"s":11,"a":91,"wi":4,"t":"نَفْقَهُ","n":"نفقه"},{"s":11,"a":91,"wi":5,"t":"كَثِيرًۭا","n":"كثيرا"},{"s":11,"a":91,"wi":6,"t":"مِّمَّا","n":"مما"},{"s":11,"a":91,"wi":7,"t":"تَقُولُ","n":"تقول"},{"s":11,"a":91,"wi":8,"t":"وَإِنَّا","n":"وانا"},{"s":11,"a":91,"wi":9,"t":"لَنَرَىٰكَ","n":"لنريك"},{"s":11,"a":91,"wi":10,"t":"فِينَا","n":"فينا"},{"s":11,"a":91,"wi":11,"t":"ضَعِيفًۭا ۖ","n":"ضعيفا"},{"s":11,"a":91,"wi":12,"t":"وَلَوْلَا","n":"ولولا"},{"s":11,"a":91,"wi":13,"t":"رَهْطُكَ","n":"رهطك"},{"s":11,"a":91,"wi":14,"t":"لَرَجَمْنَـٰكَ ۖ","n":"لرجمنـك"},{"s":11,"a":91,"wi":15,"t":"وَمَآ","n":"وما"},{"s":11,"a":91,"wi":16,"t":"أَنتَ","n":"انت"},{"s":11,"a":91,"wi":17,"t":"عَلَيْنَا","n":"علينا"},{"s":11,"a":91,"wi":18,"t":"بِعَزِيزٍۢ","n":"بعزيز"},{"s":11,"a":92,"wi":1,"t":"قَالَ","n":"قال"},{"s":11,"a":92,"wi":2,"t":"يَـٰقَوْمِ","n":"يـقوم"},{"s":11,"a":92,"wi":3,"t":"أَرَهْطِىٓ","n":"ارهطي"},{"s":11,"a":92,"wi":4,"t":"أَعَزُّ","n":"اعز"},{"s":11,"a":92,"wi":5,"t":"عَلَيْكُم","n":"عليكم"},{"s":11,"a":92,"wi":6,"t":"مِّنَ","n":"من"},{"s":11,"a":92,"wi":7,"t":"ٱللَّهِ","n":"الله"},{"s":11,"a":92,"wi":8,"t":"وَٱتَّخَذْتُمُوهُ","n":"واتخذتموه"},{"s":11,"a":92,"wi":9,"t":"وَرَآءَكُمْ","n":"وراءكم"},{"s":11,"a":92,"wi":10,"t":"ظِهْرِيًّا ۖ","n":"ظهريا"},{"s":11,"a":92,"wi":11,"t":"إِنَّ","n":"ان"},{"s":11,"a":92,"wi":12,"t":"رَبِّى","n":"ربي"},{"s":11,"a":92,"wi":13,"t":"بِمَا","n":"بما"},{"s":11,"a":92,"wi":14,"t":"تَعْمَلُونَ","n":"تعملون"},{"s":11,"a":92,"wi":15,"t":"مُحِيطٌۭ","n":"محيط"},{"s":11,"a":93,"wi":1,"t":"وَيَـٰقَوْمِ","n":"ويـقوم"},{"s":11,"a":93,"wi":2,"t":"ٱعْمَلُوا۟","n":"اعملوا"},{"s":11,"a":93,"wi":3,"t":"عَلَىٰ","n":"علي"},{"s":11,"a":93,"wi":4,"t":"مَكَانَتِكُمْ","n":"مكانتكم"},{"s":11,"a":93,"wi":5,"t":"إِنِّى","n":"اني"},{"s":11,"a":93,"wi":6,"t":"عَـٰمِلٌۭ ۖ","n":"عـمل"},{"s":11,"a":93,"wi":7,"t":"سَوْفَ","n":"سوف"},{"s":11,"a":93,"wi":8,"t":"تَعْلَمُونَ","n":"تعلمون"},{"s":11,"a":93,"wi":9,"t":"مَن","n":"من"},{"s":11,"a":93,"wi":10,"t":"يَأْتِيهِ","n":"ياتيه"},{"s":11,"a":93,"wi":11,"t":"عَذَابٌۭ","n":"عذاب"},{"s":11,"a":93,"wi":12,"t":"يُخْزِيهِ","n":"يخزيه"},{"s":11,"a":93,"wi":13,"t":"وَمَنْ","n":"ومن"},{"s":11,"a":93,"wi":14,"t":"هُوَ","n":"هو"},{"s":11,"a":93,"wi":15,"t":"كَـٰذِبٌۭ ۖ","n":"كـذب"},{"s":11,"a":93,"wi":16,"t":"وَٱرْتَقِبُوٓا۟","n":"وارتقبوا"},{"s":11,"a":93,"wi":17,"t":"إِنِّى","n":"اني"},{"s":11,"a":93,"wi":18,"t":"مَعَكُمْ","n":"معكم"},{"s":11,"a":93,"wi":19,"t":"رَقِيبٌۭ","n":"رقيب"},{"s":11,"a":94,"wi":1,"t":"وَلَمَّا","n":"ولما"},{"s":11,"a":94,"wi":2,"t":"جَآءَ","n":"جاء"},{"s":11,"a":94,"wi":3,"t":"أَمْرُنَا","n":"امرنا"},{"s":11,"a":94,"wi":4,"t":"نَجَّيْنَا","n":"نجينا"},{"s":11,"a":94,"wi":5,"t":"شُعَيْبًۭا","n":"شعيبا"},{"s":11,"a":94,"wi":6,"t":"وَٱلَّذِينَ","n":"والذين"},{"s":11,"a":94,"wi":7,"t":"ءَامَنُوا۟","n":"ءامنوا"},{"s":11,"a":94,"wi":8,"t":"مَعَهُۥ","n":"معه"},{"s":11,"a":94,"wi":9,"t":"بِرَحْمَةٍۢ","n":"برحمه"},{"s":11,"a":94,"wi":10,"t":"مِّنَّا","n":"منا"},{"s":11,"a":94,"wi":11,"t":"وَأَخَذَتِ","n":"واخذت"},{"s":11,"a":94,"wi":12,"t":"ٱلَّذِينَ","n":"الذين"},{"s":11,"a":94,"wi":13,"t":"ظَلَمُوا۟","n":"ظلموا"},{"s":11,"a":94,"wi":14,"t":"ٱلصَّيْحَةُ","n":"الصيحه"},{"s":11,"a":94,"wi":15,"t":"فَأَصْبَحُوا۟","n":"فاصبحوا"},{"s":11,"a":94,"wi":16,"t":"فِى","n":"في"},{"s":11,"a":94,"wi":17,"t":"دِيَـٰرِهِمْ","n":"ديـرهم"},{"s":11,"a":94,"wi":18,"t":"جَـٰثِمِينَ","n":"جـثمين"},{"s":11,"a":95,"wi":1,"t":"كَأَن","n":"كان"},{"s":11,"a":95,"wi":2,"t":"لَّمْ","n":"لم"},{"s":11,"a":95,"wi":3,"t":"يَغْنَوْا۟","n":"يغنوا"},{"s":11,"a":95,"wi":4,"t":"فِيهَآ ۗ","n":"فيها"},{"s":11,"a":95,"wi":5,"t":"أَلَا","n":"الا"},{"s":11,"a":95,"wi":6,"t":"بُعْدًۭا","n":"بعدا"},{"s":11,"a":95,"wi":7,"t":"لِّمَدْيَنَ","n":"لمدين"},{"s":11,"a":95,"wi":8,"t":"كَمَا","n":"كما"},{"s":11,"a":95,"wi":9,"t":"بَعِدَتْ","n":"بعدت"},{"s":11,"a":95,"wi":10,"t":"ثَمُودُ","n":"ثمود"},{"s":11,"a":96,"wi":1,"t":"وَلَقَدْ","n":"ولقد"},{"s":11,"a":96,"wi":2,"t":"أَرْسَلْنَا","n":"ارسلنا"},{"s":11,"a":96,"wi":3,"t":"مُوسَىٰ","n":"موسي"},{"s":11,"a":96,"wi":4,"t":"بِـَٔايَـٰتِنَا","n":"بـايـتنا"},{"s":11,"a":96,"wi":5,"t":"وَسُلْطَـٰنٍۢ","n":"وسلطـن"},{"s":11,"a":96,"wi":6,"t":"مُّبِينٍ","n":"مبين"},{"s":11,"a":97,"wi":1,"t":"إِلَىٰ","n":"الي"},{"s":11,"a":97,"wi":2,"t":"فِرْعَوْنَ","n":"فرعون"},{"s":11,"a":97,"wi":3,"t":"وَمَلَإِي۟هِۦ","n":"وملايه"},{"s":11,"a":97,"wi":4,"t":"فَٱتَّبَعُوٓا۟","n":"فاتبعوا"},{"s":11,"a":97,"wi":5,"t":"أَمْرَ","n":"امر"},{"s":11,"a":97,"wi":6,"t":"فِرْعَوْنَ ۖ","n":"فرعون"},{"s":11,"a":97,"wi":7,"t":"وَمَآ","n":"وما"},{"s":11,"a":97,"wi":8,"t":"أَمْرُ","n":"امر"},{"s":11,"a":97,"wi":9,"t":"فِرْعَوْنَ","n":"فرعون"},{"s":11,"a":97,"wi":10,"t":"بِرَشِيدٍۢ","n":"برشيد"}]