[{"s":9,"a":112,"wi":1,"t":"ٱلتَّـٰٓئِبُونَ","n":"التـيبون"},{"s":9,"a":112,"wi":2,"t":"ٱلْعَـٰبِدُونَ","n":"العـبدون"},{"s":9,"a":112,"wi":3,"t":"ٱلْحَـٰمِدُونَ","n":"الحـمدون"},{"s":9,"a":112,"wi":4,"t":"ٱلسَّـٰٓئِحُونَ","n":"السـيحون"},{"s":9,"a":112,"wi":5,"t":"ٱلرَّٰكِعُونَ","n":"الركعون"},{"s":9,"a":112,"wi":6,"t":"ٱلسَّـٰجِدُونَ","n":"السـجدون"},{"s":9,"a":112,"wi":7,"t":"ٱلْـَٔامِرُونَ","n":"الـامرون"},{"s":9,"a":112,"wi":8,"t":"بِٱلْمَعْرُوفِ","n":"بالمعروف"},{"s":9,"a":112,"wi":9,"t":"وَٱلنَّاهُونَ","n":"والناهون"},{"s":9,"a":112,"wi":10,"t":"عَنِ","n":"عن"},{"s":9,"a":112,"wi":11,"t":"ٱلْمُنكَرِ","n":"المنكر"},{"s":9,"a":112,"wi":12,"t":"وَٱلْحَـٰفِظُونَ","n":"والحـفظون"},{"s":9,"a":112,"wi":13,"t":"لِحُدُودِ","n":"لحدود"},{"s":9,"a":112,"wi":14,"t":"ٱللَّهِ ۗ","n":"الله"},{"s":9,"a":112,"wi":15,"t":"وَبَشِّرِ","n":"وبشر"},{"s":9,"a":112,"wi":16,"t":"ٱلْمُؤْمِنِينَ","n":"المومنين"},{"s":9,"a":113,"wi":1,"t":"مَا","n":"ما"},{"s":9,"a":113,"wi":2,"t":"كَانَ","n":"كان"},{"s":9,"a":113,"wi":3,"t":"لِلنَّبِىِّ","n":"للنبي"},{"s":9,"a":113,"wi":4,"t":"وَٱلَّذِينَ","n":"والذين"},{"s":9,"a":113,"wi":5,"t":"ءَامَنُوٓا۟","n":"ءامنوا"},{"s":9,"a":113,"wi":6,"t":"أَن","n":"ان"},{"s":9,"a":113,"wi":7,"t":"يَسْتَغْفِرُوا۟","n":"يستغفروا"},{"s":9,"a":113,"wi":8,"t":"لِلْمُشْرِكِينَ","n":"للمشركين"},{"s":9,"a":113,"wi":9,"t":"وَلَوْ","n":"ولو"},{"s":9,"a":113,"wi":10,"t":"كَانُوٓا۟","n":"كانوا"},{"s":9,"a":113,"wi":11,"t":"أُو۟لِى","n":"اولي"},{"s":9,"a":113,"wi":12,"t":"قُرْبَىٰ","n":"قربي"},{"s":9,"a":113,"wi":13,"t":"مِنۢ","n":"من"},{"s":9,"a":113,"wi":14,"t":"بَعْدِ","n":"بعد"},{"s":9,"a":113,"wi":15,"t":"مَا","n":"ما"},{"s":9,"a":113,"wi":16,"t":"تَبَيَّنَ","n":"تبين"},{"s":9,"a":113,"wi":17,"t":"لَهُمْ","n":"لهم"},{"s":9,"a":113,"wi":18,"t":"أَنَّهُمْ","n":"انهم"},{"s":9,"a":113,"wi":19,"t":"أَصْحَـٰبُ","n":"اصحـب"},{"s":9,"a":113,"wi":20,"t":"ٱلْجَحِيمِ","n":"الجحيم"},{"s":9,"a":114,"wi":1,"t":"وَمَا","n":"وما"},{"s":9,"a":114,"wi":2,"t":"كَانَ","n":"كان"},{"s":9,"a":114,"wi":3,"t":"ٱسْتِغْفَارُ","n":"استغفار"},{"s":9,"a":114,"wi":4,"t":"إِبْرَٰهِيمَ","n":"ابرهيم"},{"s":9,"a":114,"wi":5,"t":"لِأَبِيهِ","n":"لابيه"},{"s":9,"a":114,"wi":6,"t":"إِلَّا","n":"الا"},{"s":9,"a":114,"wi":7,"t":"عَن","n":"عن"},{"s":9,"a":114,"wi":8,"t":"مَّوْعِدَةٍۢ","n":"موعده"},{"s":9,"a":114,"wi":9,"t":"وَعَدَهَآ","n":"وعدها"},{"s":9,"a":114,"wi":10,"t":"إِيَّاهُ","n":"اياه"},{"s":9,"a":114,"wi":11,"t":"فَلَمَّا","n":"فلما"},{"s":9,"a":114,"wi":12,"t":"تَبَيَّنَ","n":"تبين"},{"s":9,"a":114,"wi":13,"t":"لَهُۥٓ","n":"له"},{"s":9,"a":114,"wi":14,"t":"أَنَّهُۥ","n":"انه"},{"s":9,"a":114,"wi":15,"t":"عَدُوٌّۭ","n":"عدو"},{"s":9,"a":114,"wi":16,"t":"لِّلَّهِ","n":"لله"},{"s":9,"a":114,"wi":17,"t":"تَبَرَّأَ","n":"تبرا"},{"s":9,"a":114,"wi":18,"t":"مِنْهُ ۚ","n":"منه"},{"s":9,"a":114,"wi":19,"t":"إِنَّ","n":"ان"},{"s":9,"a":114,"wi":20,"t":"إِبْرَٰهِيمَ","n":"ابرهيم"},{"s":9,"a":114,"wi":21,"t":"لَأَوَّٰهٌ","n":"لاوه"},{"s":9,"a":114,"wi":22,"t":"حَلِيمٌۭ","n":"حليم"},{"s":9,"a":115,"wi":1,"t":"وَمَا","n":"وما"},{"s":9,"a":115,"wi":2,"t":"كَانَ","n":"كان"},{"s":9,"a":115,"wi":3,"t":"ٱللَّهُ","n":"الله"},{"s":9,"a":115,"wi":4,"t":"لِيُضِلَّ","n":"ليضل"},{"s":9,"a":115,"wi":5,"t":"قَوْمًۢا","n":"قوما"},{"s":9,"a":115,"wi":6,"t":"بَعْدَ","n":"بعد"},{"s":9,"a":115,"wi":7,"t":"إِذْ","n":"اذ"},{"s":9,"a":115,"wi":8,"t":"هَدَىٰهُمْ","n":"هديهم"},{"s":9,"a":115,"wi":9,"t":"حَتَّىٰ","n":"حتي"},{"s":9,"a":115,"wi":10,"t":"يُبَيِّنَ","n":"يبين"},{"s":9,"a":115,"wi":11,"t":"لَهُم","n":"لهم"},{"s":9,"a":115,"wi":12,"t":"مَّا","n":"ما"},{"s":9,"a":115,"wi":13,"t":"يَتَّقُونَ ۚ","n":"يتقون"},{"s":9,"a":115,"wi":14,"t":"إِنَّ","n":"ان"},{"s":9,"a":115,"wi":15,"t":"ٱللَّهَ","n":"الله"},{"s":9,"a":115,"wi":16,"t":"بِكُلِّ","n":"بكل"},{"s":9,"a":115,"wi":17,"t":"شَىْءٍ","n":"شيء"},{"s":9,"a":115,"wi":18,"t":"عَلِيمٌ","n":"عليم"},{"s":9,"a":116,"wi":1,"t":"إِنَّ","n":"ان"},{"s":9,"a":116,"wi":2,"t":"ٱللَّهَ","n":"الله"},{"s":9,"a":116,"wi":3,"t":"لَهُۥ","n":"له"},{"s":9,"a":116,"wi":4,"t":"مُلْكُ","n":"ملك"},{"s":9,"a":116,"wi":5,"t":"ٱلسَّمَـٰوَٰتِ","n":"السمـوت"},{"s":9,"a":116,"wi":6,"t":"وَٱلْأَرْضِ ۖ","n":"والارض"},{"s":9,"a":116,"wi":7,"t":"يُحْىِۦ","n":"يحي"},{"s":9,"a":116,"wi":8,"t":"وَيُمِيتُ ۚ","n":"ويميت"},{"s":9,"a":116,"wi":9,"t":"وَمَا","n":"وما"},{"s":9,"a":116,"wi":10,"t":"لَكُم","n":"لكم"},{"s":9,"a":116,"wi":11,"t":"مِّن","n":"من"},{"s":9,"a":116,"wi":12,"t":"دُونِ","n":"دون"},{"s":9,"a":116,"wi":13,"t":"ٱللَّهِ","n":"الله"},{"s":9,"a":116,"wi":14,"t":"مِن","n":"من"},{"s":9,"a":116,"wi":15,"t":"وَلِىٍّۢ","n":"ولي"},{"s":9,"a":116,"wi":16,"t":"وَلَا","n":"ولا"},{"s":9,"a":116,"wi":17,"t":"نَصِيرٍۢ","n":"نصير"},{"s":9,"a":117,"wi":1,"t":"لَّقَد","n":"لقد"},{"s":9,"a":117,"wi":2,"t":"تَّابَ","n":"تاب"},{"s":9,"a":117,"wi":3,"t":"ٱللَّهُ","n":"الله"},{"s":9,"a":117,"wi":4,"t":"عَلَى","n":"علي"},{"s":9,"a":117,"wi":5,"t":"ٱلنَّبِىِّ","n":"النبي"},{"s":9,"a":117,"wi":6,"t":"وَٱلْمُهَـٰجِرِينَ","n":"والمهـجرين"},{"s":9,"a":117,"wi":7,"t":"وَٱلْأَنصَارِ","n":"والانصار"},{"s":9,"a":117,"wi":8,"t":"ٱلَّذِينَ","n":"الذين"},{"s":9,"a":117,"wi":9,"t":"ٱتَّبَعُوهُ","n":"اتبعوه"},{"s":9,"a":117,"wi":10,"t":"فِى","n":"في"},{"s":9,"a":117,"wi":11,"t":"سَاعَةِ","n":"ساعه"},{"s":9,"a":117,"wi":12,"t":"ٱلْعُسْرَةِ","n":"العسره"},{"s":9,"a":117,"wi":13,"t":"مِنۢ","n":"من"},{"s":9,"a":117,"wi":14,"t":"بَعْدِ","n":"بعد"},{"s":9,"a":117,"wi":15,"t":"مَا","n":"ما"},{"s":9,"a":117,"wi":16,"t":"كَادَ","n":"كاد"},{"s":9,"a":117,"wi":17,"t":"يَزِيغُ","n":"يزيغ"},{"s":9,"a":117,"wi":18,"t":"قُلُوبُ","n":"قلوب"},{"s":9,"a":117,"wi":19,"t":"فَرِيقٍۢ","n":"فريق"},{"s":9,"a":117,"wi":20,"t":"مِّنْهُمْ","n":"منهم"},{"s":9,"a":117,"wi":21,"t":"ثُمَّ","n":"ثم"},{"s":9,"a":117,"wi":22,"t":"تَابَ","n":"تاب"},{"s":9,"a":117,"wi":23,"t":"عَلَيْهِمْ ۚ","n":"عليهم"},{"s":9,"a":117,"wi":24,"t":"إِنَّهُۥ","n":"انه"},{"s":9,"a":117,"wi":25,"t":"بِهِمْ","n":"بهم"},{"s":9,"a":117,"wi":26,"t":"رَءُوفٌۭ","n":"رءوف"},{"s":9,"a":117,"wi":27,"t":"رَّحِيمٌۭ","n":"رحيم"}]