[{"s":11,"a":72,"wi":1,"t":"قَالَتْ","n":"قالت","ln":1},{"s":11,"a":72,"wi":2,"t":"يَـٰوَيْلَتَىٰٓ","n":"يـويلتي","ln":1},{"s":11,"a":72,"wi":3,"t":"ءَأَلِدُ","n":"ءالد","ln":1},{"s":11,"a":72,"wi":4,"t":"وَأَنَا۠","n":"وانا","ln":1},{"s":11,"a":72,"wi":5,"t":"عَجُوزٌۭ","n":"عجوز","ln":1},{"s":11,"a":72,"wi":6,"t":"وَهَـٰذَا","n":"وهـذا","ln":1},{"s":11,"a":72,"wi":7,"t":"بَعْلِى","n":"بعلي","ln":1},{"s":11,"a":72,"wi":8,"t":"شَيْخًا ۖ","n":"شيخا","ln":1},{"s":11,"a":72,"wi":9,"t":"إِنَّ","n":"ان","ln":1},{"s":11,"a":72,"wi":10,"t":"هَـٰذَا","n":"هـذا","ln":1},{"s":11,"a":72,"wi":11,"t":"لَشَىْءٌ","n":"لشيء","ln":2},{"s":11,"a":72,"wi":12,"t":"عَجِيبٌۭ","n":"عجيب","ln":2},{"s":11,"a":73,"wi":1,"t":"قَالُوٓا۟","n":"قالوا","ln":2},{"s":11,"a":73,"wi":2,"t":"أَتَعْجَبِينَ","n":"اتعجبين","ln":2},{"s":11,"a":73,"wi":3,"t":"مِنْ","n":"من","ln":2},{"s":11,"a":73,"wi":4,"t":"أَمْرِ","n":"امر","ln":2},{"s":11,"a":73,"wi":5,"t":"ٱللَّهِ ۖ","n":"الله","ln":2},{"s":11,"a":73,"wi":6,"t":"رَحْمَتُ","n":"رحمت","ln":2},{"s":11,"a":73,"wi":7,"t":"ٱللَّهِ","n":"الله","ln":2},{"s":11,"a":73,"wi":8,"t":"وَبَرَكَـٰتُهُۥ","n":"وبركـته","ln":3},{"s":11,"a":73,"wi":9,"t":"عَلَيْكُمْ","n":"عليكم","ln":3},{"s":11,"a":73,"wi":10,"t":"أَهْلَ","n":"اهل","ln":3},{"s":11,"a":73,"wi":11,"t":"ٱلْبَيْتِ ۚ","n":"البيت","ln":3},{"s":11,"a":73,"wi":12,"t":"إِنَّهُۥ","n":"انه","ln":3},{"s":11,"a":73,"wi":13,"t":"حَمِيدٌۭ","n":"حميد","ln":3},{"s":11,"a":73,"wi":14,"t":"مَّجِيدٌۭ","n":"مجيد","ln":3},{"s":11,"a":74,"wi":1,"t":"فَلَمَّا","n":"فلما","ln":3},{"s":11,"a":74,"wi":2,"t":"ذَهَبَ","n":"ذهب","ln":3},{"s":11,"a":74,"wi":3,"t":"عَنْ","n":"عن","ln":4},{"s":11,"a":74,"wi":4,"t":"إِبْرَٰهِيمَ","n":"ابرهيم","ln":4},{"s":11,"a":74,"wi":5,"t":"ٱلرَّوْعُ","n":"الروع","ln":4},{"s":11,"a":74,"wi":6,"t":"وَجَآءَتْهُ","n":"وجاءته","ln":4},{"s":11,"a":74,"wi":7,"t":"ٱلْبُشْرَىٰ","n":"البشري","ln":4},{"s":11,"a":74,"wi":8,"t":"يُجَـٰدِلُنَا","n":"يجـدلنا","ln":4},{"s":11,"a":74,"wi":9,"t":"فِى","n":"في","ln":4},{"s":11,"a":74,"wi":10,"t":"قَوْمِ","n":"قوم","ln":4},{"s":11,"a":74,"wi":11,"t":"لُوطٍ","n":"لوط","ln":4},{"s":11,"a":75,"wi":1,"t":"إِنَّ","n":"ان","ln":5},{"s":11,"a":75,"wi":2,"t":"إِبْرَٰهِيمَ","n":"ابرهيم","ln":5},{"s":11,"a":75,"wi":3,"t":"لَحَلِيمٌ","n":"لحليم","ln":5},{"s":11,"a":75,"wi":4,"t":"أَوَّٰهٌۭ","n":"اوه","ln":5},{"s":11,"a":75,"wi":5,"t":"مُّنِيبٌۭ","n":"منيب","ln":5},{"s":11,"a":76,"wi":1,"t":"يَـٰٓإِبْرَٰهِيمُ","n":"يـابرهيم","ln":5},{"s":11,"a":76,"wi":2,"t":"أَعْرِضْ","n":"اعرض","ln":5},{"s":11,"a":76,"wi":3,"t":"عَنْ","n":"عن","ln":5},{"s":11,"a":76,"wi":4,"t":"هَـٰذَآ ۖ","n":"هـذا","ln":5},{"s":11,"a":76,"wi":5,"t":"إِنَّهُۥ","n":"انه","ln":5},{"s":11,"a":76,"wi":6,"t":"قَدْ","n":"قد","ln":6},{"s":11,"a":76,"wi":7,"t":"جَآءَ","n":"جاء","ln":6},{"s":11,"a":76,"wi":8,"t":"أَمْرُ","n":"امر","ln":6},{"s":11,"a":76,"wi":9,"t":"رَبِّكَ ۖ","n":"ربك","ln":6},{"s":11,"a":76,"wi":10,"t":"وَإِنَّهُمْ","n":"وانهم","ln":6},{"s":11,"a":76,"wi":11,"t":"ءَاتِيهِمْ","n":"ءاتيهم","ln":6},{"s":11,"a":76,"wi":12,"t":"عَذَابٌ","n":"عذاب","ln":6},{"s":11,"a":76,"wi":13,"t":"غَيْرُ","n":"غير","ln":6},{"s":11,"a":76,"wi":14,"t":"مَرْدُودٍۢ","n":"مردود","ln":6},{"s":11,"a":77,"wi":1,"t":"وَلَمَّا","n":"ولما","ln":6},{"s":11,"a":77,"wi":2,"t":"جَآءَتْ","n":"جاءت","ln":7},{"s":11,"a":77,"wi":3,"t":"رُسُلُنَا","n":"رسلنا","ln":7},{"s":11,"a":77,"wi":4,"t":"لُوطًۭا","n":"لوطا","ln":7},{"s":11,"a":77,"wi":5,"t":"سِىٓءَ","n":"سيء","ln":7},{"s":11,"a":77,"wi":6,"t":"بِهِمْ","n":"بهم","ln":7},{"s":11,"a":77,"wi":7,"t":"وَضَاقَ","n":"وضاق","ln":7},{"s":11,"a":77,"wi":8,"t":"بِهِمْ","n":"بهم","ln":7},{"s":11,"a":77,"wi":9,"t":"ذَرْعًۭا","n":"ذرعا","ln":7},{"s":11,"a":77,"wi":10,"t":"وَقَالَ","n":"وقال","ln":7},{"s":11,"a":77,"wi":11,"t":"هَـٰذَا","n":"هـذا","ln":7},{"s":11,"a":77,"wi":12,"t":"يَوْمٌ","n":"يوم","ln":8},{"s":11,"a":77,"wi":13,"t":"عَصِيبٌۭ","n":"عصيب","ln":8},{"s":11,"a":78,"wi":1,"t":"وَجَآءَهُۥ","n":"وجاءه","ln":8},{"s":11,"a":78,"wi":2,"t":"قَوْمُهُۥ","n":"قومه","ln":8},{"s":11,"a":78,"wi":3,"t":"يُهْرَعُونَ","n":"يهرعون","ln":8},{"s":11,"a":78,"wi":4,"t":"إِلَيْهِ","n":"اليه","ln":8},{"s":11,"a":78,"wi":5,"t":"وَمِن","n":"ومن","ln":8},{"s":11,"a":78,"wi":6,"t":"قَبْلُ","n":"قبل","ln":8},{"s":11,"a":78,"wi":7,"t":"كَانُوا۟","n":"كانوا","ln":8},{"s":11,"a":78,"wi":8,"t":"يَعْمَلُونَ","n":"يعملون","ln":9},{"s":11,"a":78,"wi":9,"t":"ٱلسَّيِّـَٔاتِ ۚ","n":"السيـات","ln":9},{"s":11,"a":78,"wi":10,"t":"قَالَ","n":"قال","ln":9},{"s":11,"a":78,"wi":11,"t":"يَـٰقَوْمِ","n":"يـقوم","ln":9},{"s":11,"a":78,"wi":12,"t":"هَـٰٓؤُلَآءِ","n":"هـولاء","ln":9},{"s":11,"a":78,"wi":13,"t":"بَنَاتِى","n":"بناتي","ln":9},{"s":11,"a":78,"wi":14,"t":"هُنَّ","n":"هن","ln":9},{"s":11,"a":78,"wi":15,"t":"أَطْهَرُ","n":"اطهر","ln":9},{"s":11,"a":78,"wi":16,"t":"لَكُمْ ۖ","n":"لكم","ln":9},{"s":11,"a":78,"wi":17,"t":"فَٱتَّقُوا۟","n":"فاتقوا","ln":10},{"s":11,"a":78,"wi":18,"t":"ٱللَّهَ","n":"الله","ln":10},{"s":11,"a":78,"wi":19,"t":"وَلَا","n":"ولا","ln":10},{"s":11,"a":78,"wi":20,"t":"تُخْزُونِ","n":"تخزون","ln":10},{"s":11,"a":78,"wi":21,"t":"فِى","n":"في","ln":10},{"s":11,"a":78,"wi":22,"t":"ضَيْفِىٓ ۖ","n":"ضيفي","ln":10},{"s":11,"a":78,"wi":23,"t":"أَلَيْسَ","n":"اليس","ln":10},{"s":11,"a":78,"wi":24,"t":"مِنكُمْ","n":"منكم","ln":10},{"s":11,"a":78,"wi":25,"t":"رَجُلٌۭ","n":"رجل","ln":10},{"s":11,"a":78,"wi":26,"t":"رَّشِيدٌۭ","n":"رشيد","ln":10},{"s":11,"a":79,"wi":1,"t":"قَالُوا۟","n":"قالوا","ln":11},{"s":11,"a":79,"wi":2,"t":"لَقَدْ","n":"لقد","ln":11},{"s":11,"a":79,"wi":3,"t":"عَلِمْتَ","n":"علمت","ln":11},{"s":11,"a":79,"wi":4,"t":"مَا","n":"ما","ln":11},{"s":11,"a":79,"wi":5,"t":"لَنَا","n":"لنا","ln":11},{"s":11,"a":79,"wi":6,"t":"فِى","n":"في","ln":11},{"s":11,"a":79,"wi":7,"t":"بَنَاتِكَ","n":"بناتك","ln":11},{"s":11,"a":79,"wi":8,"t":"مِنْ","n":"من","ln":11},{"s":11,"a":79,"wi":9,"t":"حَقٍّۢ","n":"حق","ln":11},{"s":11,"a":79,"wi":10,"t":"وَإِنَّكَ","n":"وانك","ln":11},{"s":11,"a":79,"wi":11,"t":"لَتَعْلَمُ","n":"لتعلم","ln":11},{"s":11,"a":79,"wi":12,"t":"مَا","n":"ما","ln":11},{"s":11,"a":79,"wi":13,"t":"نُرِيدُ","n":"نريد","ln":11},{"s":11,"a":80,"wi":1,"t":"قَالَ","n":"قال","ln":12},{"s":11,"a":80,"wi":2,"t":"لَوْ","n":"لو","ln":12},{"s":11,"a":80,"wi":3,"t":"أَنَّ","n":"ان","ln":12},{"s":11,"a":80,"wi":4,"t":"لِى","n":"لي","ln":12},{"s":11,"a":80,"wi":5,"t":"بِكُمْ","n":"بكم","ln":12},{"s":11,"a":80,"wi":6,"t":"قُوَّةً","n":"قوه","ln":12},{"s":11,"a":80,"wi":7,"t":"أَوْ","n":"او","ln":12},{"s":11,"a":80,"wi":8,"t":"ءَاوِىٓ","n":"ءاوي","ln":12},{"s":11,"a":80,"wi":9,"t":"إِلَىٰ","n":"الي","ln":12},{"s":11,"a":80,"wi":10,"t":"رُكْنٍۢ","n":"ركن","ln":12},{"s":11,"a":80,"wi":11,"t":"شَدِيدٍۢ","n":"شديد","ln":12},{"s":11,"a":81,"wi":1,"t":"قَالُوا۟","n":"قالوا","ln":12},{"s":11,"a":81,"wi":2,"t":"يَـٰلُوطُ","n":"يـلوط","ln":13},{"s":11,"a":81,"wi":3,"t":"إِنَّا","n":"انا","ln":13},{"s":11,"a":81,"wi":4,"t":"رُسُلُ","n":"رسل","ln":13},{"s":11,"a":81,"wi":5,"t":"رَبِّكَ","n":"ربك","ln":13},{"s":11,"a":81,"wi":6,"t":"لَن","n":"لن","ln":13},{"s":11,"a":81,"wi":7,"t":"يَصِلُوٓا۟","n":"يصلوا","ln":13},{"s":11,"a":81,"wi":8,"t":"إِلَيْكَ ۖ","n":"اليك","ln":13},{"s":11,"a":81,"wi":9,"t":"فَأَسْرِ","n":"فاسر","ln":13},{"s":11,"a":81,"wi":10,"t":"بِأَهْلِكَ","n":"باهلك","ln":13},{"s":11,"a":81,"wi":11,"t":"بِقِطْعٍۢ","n":"بقطع","ln":13},{"s":11,"a":81,"wi":12,"t":"مِّنَ","n":"من","ln":14},{"s":11,"a":81,"wi":13,"t":"ٱلَّيْلِ","n":"اليل","ln":14},{"s":11,"a":81,"wi":14,"t":"وَلَا","n":"ولا","ln":14},{"s":11,"a":81,"wi":15,"t":"يَلْتَفِتْ","n":"يلتفت","ln":14},{"s":11,"a":81,"wi":16,"t":"مِنكُمْ","n":"منكم","ln":14},{"s":11,"a":81,"wi":17,"t":"أَحَدٌ","n":"احد","ln":14},{"s":11,"a":81,"wi":18,"t":"إِلَّا","n":"الا","ln":14},{"s":11,"a":81,"wi":19,"t":"ٱمْرَأَتَكَ ۖ","n":"امراتك","ln":14},{"s":11,"a":81,"wi":20,"t":"إِنَّهُۥ","n":"انه","ln":14},{"s":11,"a":81,"wi":21,"t":"مُصِيبُهَا","n":"مصيبها","ln":14},{"s":11,"a":81,"wi":22,"t":"مَآ","n":"ما","ln":15},{"s":11,"a":81,"wi":23,"t":"أَصَابَهُمْ ۚ","n":"اصابهم","ln":15},{"s":11,"a":81,"wi":24,"t":"إِنَّ","n":"ان","ln":15},{"s":11,"a":81,"wi":25,"t":"مَوْعِدَهُمُ","n":"موعدهم","ln":15},{"s":11,"a":81,"wi":26,"t":"ٱلصُّبْحُ ۚ","n":"الصبح","ln":15},{"s":11,"a":81,"wi":27,"t":"أَلَيْسَ","n":"اليس","ln":15},{"s":11,"a":81,"wi":28,"t":"ٱلصُّبْحُ","n":"الصبح","ln":15},{"s":11,"a":81,"wi":29,"t":"بِقَرِيبٍۢ","n":"بقريب","ln":15}]