[{"s":4,"a":155,"wi":1,"t":"فَبِمَا","n":"فبما"},{"s":4,"a":155,"wi":2,"t":"نَقْضِهِم","n":"نقضهم"},{"s":4,"a":155,"wi":3,"t":"مِّيثَـٰقَهُمْ","n":"ميثـقهم"},{"s":4,"a":155,"wi":4,"t":"وَكُفْرِهِم","n":"وكفرهم"},{"s":4,"a":155,"wi":5,"t":"بِـَٔايَـٰتِ","n":"بـايـت"},{"s":4,"a":155,"wi":6,"t":"ٱللَّهِ","n":"الله"},{"s":4,"a":155,"wi":7,"t":"وَقَتْلِهِمُ","n":"وقتلهم"},{"s":4,"a":155,"wi":8,"t":"ٱلْأَنۢبِيَآءَ","n":"الانبياء"},{"s":4,"a":155,"wi":9,"t":"بِغَيْرِ","n":"بغير"},{"s":4,"a":155,"wi":10,"t":"حَقٍّۢ","n":"حق"},{"s":4,"a":155,"wi":11,"t":"وَقَوْلِهِمْ","n":"وقولهم"},{"s":4,"a":155,"wi":12,"t":"قُلُوبُنَا","n":"قلوبنا"},{"s":4,"a":155,"wi":13,"t":"غُلْفٌۢ ۚ","n":"غلف"},{"s":4,"a":155,"wi":14,"t":"بَلْ","n":"بل"},{"s":4,"a":155,"wi":15,"t":"طَبَعَ","n":"طبع"},{"s":4,"a":155,"wi":16,"t":"ٱللَّهُ","n":"الله"},{"s":4,"a":155,"wi":17,"t":"عَلَيْهَا","n":"عليها"},{"s":4,"a":155,"wi":18,"t":"بِكُفْرِهِمْ","n":"بكفرهم"},{"s":4,"a":155,"wi":19,"t":"فَلَا","n":"فلا"},{"s":4,"a":155,"wi":20,"t":"يُؤْمِنُونَ","n":"يومنون"},{"s":4,"a":155,"wi":21,"t":"إِلَّا","n":"الا"},{"s":4,"a":155,"wi":22,"t":"قَلِيلًۭا","n":"قليلا"},{"s":4,"a":156,"wi":1,"t":"وَبِكُفْرِهِمْ","n":"وبكفرهم"},{"s":4,"a":156,"wi":2,"t":"وَقَوْلِهِمْ","n":"وقولهم"},{"s":4,"a":156,"wi":3,"t":"عَلَىٰ","n":"علي"},{"s":4,"a":156,"wi":4,"t":"مَرْيَمَ","n":"مريم"},{"s":4,"a":156,"wi":5,"t":"بُهْتَـٰنًا","n":"بهتـنا"},{"s":4,"a":156,"wi":6,"t":"عَظِيمًۭا","n":"عظيما"},{"s":4,"a":157,"wi":1,"t":"وَقَوْلِهِمْ","n":"وقولهم"},{"s":4,"a":157,"wi":2,"t":"إِنَّا","n":"انا"},{"s":4,"a":157,"wi":3,"t":"قَتَلْنَا","n":"قتلنا"},{"s":4,"a":157,"wi":4,"t":"ٱلْمَسِيحَ","n":"المسيح"},{"s":4,"a":157,"wi":5,"t":"عِيسَى","n":"عيسي"},{"s":4,"a":157,"wi":6,"t":"ٱبْنَ","n":"ابن"},{"s":4,"a":157,"wi":7,"t":"مَرْيَمَ","n":"مريم"},{"s":4,"a":157,"wi":8,"t":"رَسُولَ","n":"رسول"},{"s":4,"a":157,"wi":9,"t":"ٱللَّهِ","n":"الله"},{"s":4,"a":157,"wi":10,"t":"وَمَا","n":"وما"},{"s":4,"a":157,"wi":11,"t":"قَتَلُوهُ","n":"قتلوه"},{"s":4,"a":157,"wi":12,"t":"وَمَا","n":"وما"},{"s":4,"a":157,"wi":13,"t":"صَلَبُوهُ","n":"صلبوه"},{"s":4,"a":157,"wi":14,"t":"وَلَـٰكِن","n":"ولـكن"},{"s":4,"a":157,"wi":15,"t":"شُبِّهَ","n":"شبه"},{"s":4,"a":157,"wi":16,"t":"لَهُمْ ۚ","n":"لهم"},{"s":4,"a":157,"wi":17,"t":"وَإِنَّ","n":"وان"},{"s":4,"a":157,"wi":18,"t":"ٱلَّذِينَ","n":"الذين"},{"s":4,"a":157,"wi":19,"t":"ٱخْتَلَفُوا۟","n":"اختلفوا"},{"s":4,"a":157,"wi":20,"t":"فِيهِ","n":"فيه"},{"s":4,"a":157,"wi":21,"t":"لَفِى","n":"لفي"},{"s":4,"a":157,"wi":22,"t":"شَكٍّۢ","n":"شك"},{"s":4,"a":157,"wi":23,"t":"مِّنْهُ ۚ","n":"منه"},{"s":4,"a":157,"wi":24,"t":"مَا","n":"ما"},{"s":4,"a":157,"wi":25,"t":"لَهُم","n":"لهم"},{"s":4,"a":157,"wi":26,"t":"بِهِۦ","n":"به"},{"s":4,"a":157,"wi":27,"t":"مِنْ","n":"من"},{"s":4,"a":157,"wi":28,"t":"عِلْمٍ","n":"علم"},{"s":4,"a":157,"wi":29,"t":"إِلَّا","n":"الا"},{"s":4,"a":157,"wi":30,"t":"ٱتِّبَاعَ","n":"اتباع"},{"s":4,"a":157,"wi":31,"t":"ٱلظَّنِّ ۚ","n":"الظن"},{"s":4,"a":157,"wi":32,"t":"وَمَا","n":"وما"},{"s":4,"a":157,"wi":33,"t":"قَتَلُوهُ","n":"قتلوه"},{"s":4,"a":157,"wi":34,"t":"يَقِينًۢا","n":"يقينا"},{"s":4,"a":158,"wi":1,"t":"بَل","n":"بل"},{"s":4,"a":158,"wi":2,"t":"رَّفَعَهُ","n":"رفعه"},{"s":4,"a":158,"wi":3,"t":"ٱللَّهُ","n":"الله"},{"s":4,"a":158,"wi":4,"t":"إِلَيْهِ ۚ","n":"اليه"},{"s":4,"a":158,"wi":5,"t":"وَكَانَ","n":"وكان"},{"s":4,"a":158,"wi":6,"t":"ٱللَّهُ","n":"الله"},{"s":4,"a":158,"wi":7,"t":"عَزِيزًا","n":"عزيزا"},{"s":4,"a":158,"wi":8,"t":"حَكِيمًۭا","n":"حكيما"},{"s":4,"a":159,"wi":1,"t":"وَإِن","n":"وان"},{"s":4,"a":159,"wi":2,"t":"مِّنْ","n":"من"},{"s":4,"a":159,"wi":3,"t":"أَهْلِ","n":"اهل"},{"s":4,"a":159,"wi":4,"t":"ٱلْكِتَـٰبِ","n":"الكتـب"},{"s":4,"a":159,"wi":5,"t":"إِلَّا","n":"الا"},{"s":4,"a":159,"wi":6,"t":"لَيُؤْمِنَنَّ","n":"ليومنن"},{"s":4,"a":159,"wi":7,"t":"بِهِۦ","n":"به"},{"s":4,"a":159,"wi":8,"t":"قَبْلَ","n":"قبل"},{"s":4,"a":159,"wi":9,"t":"مَوْتِهِۦ ۖ","n":"موته"},{"s":4,"a":159,"wi":10,"t":"وَيَوْمَ","n":"ويوم"},{"s":4,"a":159,"wi":11,"t":"ٱلْقِيَـٰمَةِ","n":"القيـمه"},{"s":4,"a":159,"wi":12,"t":"يَكُونُ","n":"يكون"},{"s":4,"a":159,"wi":13,"t":"عَلَيْهِمْ","n":"عليهم"},{"s":4,"a":159,"wi":14,"t":"شَهِيدًۭا","n":"شهيدا"},{"s":4,"a":160,"wi":1,"t":"فَبِظُلْمٍۢ","n":"فبظلم"},{"s":4,"a":160,"wi":2,"t":"مِّنَ","n":"من"},{"s":4,"a":160,"wi":3,"t":"ٱلَّذِينَ","n":"الذين"},{"s":4,"a":160,"wi":4,"t":"هَادُوا۟","n":"هادوا"},{"s":4,"a":160,"wi":5,"t":"حَرَّمْنَا","n":"حرمنا"},{"s":4,"a":160,"wi":6,"t":"عَلَيْهِمْ","n":"عليهم"},{"s":4,"a":160,"wi":7,"t":"طَيِّبَـٰتٍ","n":"طيبـت"},{"s":4,"a":160,"wi":8,"t":"أُحِلَّتْ","n":"احلت"},{"s":4,"a":160,"wi":9,"t":"لَهُمْ","n":"لهم"},{"s":4,"a":160,"wi":10,"t":"وَبِصَدِّهِمْ","n":"وبصدهم"},{"s":4,"a":160,"wi":11,"t":"عَن","n":"عن"},{"s":4,"a":160,"wi":12,"t":"سَبِيلِ","n":"سبيل"},{"s":4,"a":160,"wi":13,"t":"ٱللَّهِ","n":"الله"},{"s":4,"a":160,"wi":14,"t":"كَثِيرًۭا","n":"كثيرا"},{"s":4,"a":161,"wi":1,"t":"وَأَخْذِهِمُ","n":"واخذهم"},{"s":4,"a":161,"wi":2,"t":"ٱلرِّبَوٰا۟","n":"الربوا"},{"s":4,"a":161,"wi":3,"t":"وَقَدْ","n":"وقد"},{"s":4,"a":161,"wi":4,"t":"نُهُوا۟","n":"نهوا"},{"s":4,"a":161,"wi":5,"t":"عَنْهُ","n":"عنه"},{"s":4,"a":161,"wi":6,"t":"وَأَكْلِهِمْ","n":"واكلهم"},{"s":4,"a":161,"wi":7,"t":"أَمْوَٰلَ","n":"امول"},{"s":4,"a":161,"wi":8,"t":"ٱلنَّاسِ","n":"الناس"},{"s":4,"a":161,"wi":9,"t":"بِٱلْبَـٰطِلِ ۚ","n":"بالبـطل"},{"s":4,"a":161,"wi":10,"t":"وَأَعْتَدْنَا","n":"واعتدنا"},{"s":4,"a":161,"wi":11,"t":"لِلْكَـٰفِرِينَ","n":"للكـفرين"},{"s":4,"a":161,"wi":12,"t":"مِنْهُمْ","n":"منهم"},{"s":4,"a":161,"wi":13,"t":"عَذَابًا","n":"عذابا"},{"s":4,"a":161,"wi":14,"t":"أَلِيمًۭا","n":"اليما"},{"s":4,"a":162,"wi":1,"t":"لَّـٰكِنِ","n":"لـكن"},{"s":4,"a":162,"wi":2,"t":"ٱلرَّٰسِخُونَ","n":"الرسخون"},{"s":4,"a":162,"wi":3,"t":"فِى","n":"في"},{"s":4,"a":162,"wi":4,"t":"ٱلْعِلْمِ","n":"العلم"},{"s":4,"a":162,"wi":5,"t":"مِنْهُمْ","n":"منهم"},{"s":4,"a":162,"wi":6,"t":"وَٱلْمُؤْمِنُونَ","n":"والمومنون"},{"s":4,"a":162,"wi":7,"t":"يُؤْمِنُونَ","n":"يومنون"},{"s":4,"a":162,"wi":8,"t":"بِمَآ","n":"بما"},{"s":4,"a":162,"wi":9,"t":"أُنزِلَ","n":"انزل"},{"s":4,"a":162,"wi":10,"t":"إِلَيْكَ","n":"اليك"},{"s":4,"a":162,"wi":11,"t":"وَمَآ","n":"وما"},{"s":4,"a":162,"wi":12,"t":"أُنزِلَ","n":"انزل"},{"s":4,"a":162,"wi":13,"t":"مِن","n":"من"},{"s":4,"a":162,"wi":14,"t":"قَبْلِكَ ۚ","n":"قبلك"},{"s":4,"a":162,"wi":15,"t":"وَٱلْمُقِيمِينَ","n":"والمقيمين"},{"s":4,"a":162,"wi":16,"t":"ٱلصَّلَوٰةَ ۚ","n":"الصلوه"},{"s":4,"a":162,"wi":17,"t":"وَٱلْمُؤْتُونَ","n":"والموتون"},{"s":4,"a":162,"wi":18,"t":"ٱلزَّكَوٰةَ","n":"الزكوه"},{"s":4,"a":162,"wi":19,"t":"وَٱلْمُؤْمِنُونَ","n":"والمومنون"},{"s":4,"a":162,"wi":20,"t":"بِٱللَّهِ","n":"بالله"},{"s":4,"a":162,"wi":21,"t":"وَٱلْيَوْمِ","n":"واليوم"},{"s":4,"a":162,"wi":22,"t":"ٱلْـَٔاخِرِ","n":"الـاخر"},{"s":4,"a":162,"wi":23,"t":"أُو۟لَـٰٓئِكَ","n":"اولـيك"},{"s":4,"a":162,"wi":24,"t":"سَنُؤْتِيهِمْ","n":"سنوتيهم"},{"s":4,"a":162,"wi":25,"t":"أَجْرًا","n":"اجرا"},{"s":4,"a":162,"wi":26,"t":"عَظِيمًا","n":"عظيما"}]