[{"s":19,"a":1,"wi":1,"t":"كٓهيعٓصٓ","n":"كهيعص","ln":3},{"s":19,"a":2,"wi":1,"t":"ذِكْرُ","n":"ذكر","ln":3},{"s":19,"a":2,"wi":2,"t":"رَحْمَتِ","n":"رحمت","ln":3},{"s":19,"a":2,"wi":3,"t":"رَبِّكَ","n":"ربك","ln":3},{"s":19,"a":2,"wi":4,"t":"عَبْدَهُۥ","n":"عبده","ln":3},{"s":19,"a":2,"wi":5,"t":"زَكَرِيَّآ","n":"زكريا","ln":3},{"s":19,"a":3,"wi":1,"t":"إِذْ","n":"اذ","ln":4},{"s":19,"a":3,"wi":2,"t":"نَادَىٰ","n":"نادي","ln":4},{"s":19,"a":3,"wi":3,"t":"رَبَّهُۥ","n":"ربه","ln":4},{"s":19,"a":3,"wi":4,"t":"نِدَآءً","n":"نداء","ln":4},{"s":19,"a":3,"wi":5,"t":"خَفِيًّۭا","n":"خفيا","ln":4},{"s":19,"a":4,"wi":1,"t":"قَالَ","n":"قال","ln":4},{"s":19,"a":4,"wi":2,"t":"رَبِّ","n":"رب","ln":4},{"s":19,"a":4,"wi":3,"t":"إِنِّى","n":"اني","ln":4},{"s":19,"a":4,"wi":4,"t":"وَهَنَ","n":"وهن","ln":4},{"s":19,"a":4,"wi":5,"t":"ٱلْعَظْمُ","n":"العظم","ln":4},{"s":19,"a":4,"wi":6,"t":"مِنِّى","n":"مني","ln":5},{"s":19,"a":4,"wi":7,"t":"وَٱشْتَعَلَ","n":"واشتعل","ln":5},{"s":19,"a":4,"wi":8,"t":"ٱلرَّأْسُ","n":"الراس","ln":5},{"s":19,"a":4,"wi":9,"t":"شَيْبًۭا","n":"شيبا","ln":5},{"s":19,"a":4,"wi":10,"t":"وَلَمْ","n":"ولم","ln":5},{"s":19,"a":4,"wi":11,"t":"أَكُنۢ","n":"اكن","ln":5},{"s":19,"a":4,"wi":12,"t":"بِدُعَآئِكَ","n":"بدعايك","ln":5},{"s":19,"a":4,"wi":13,"t":"رَبِّ","n":"رب","ln":5},{"s":19,"a":4,"wi":14,"t":"شَقِيًّۭا","n":"شقيا","ln":6},{"s":19,"a":5,"wi":1,"t":"وَإِنِّى","n":"واني","ln":6},{"s":19,"a":5,"wi":2,"t":"خِفْتُ","n":"خفت","ln":6},{"s":19,"a":5,"wi":3,"t":"ٱلْمَوَٰلِىَ","n":"المولي","ln":6},{"s":19,"a":5,"wi":4,"t":"مِن","n":"من","ln":6},{"s":19,"a":5,"wi":5,"t":"وَرَآءِى","n":"وراءي","ln":6},{"s":19,"a":5,"wi":6,"t":"وَكَانَتِ","n":"وكانت","ln":6},{"s":19,"a":5,"wi":7,"t":"ٱمْرَأَتِى","n":"امراتي","ln":7},{"s":19,"a":5,"wi":8,"t":"عَاقِرًۭا","n":"عاقرا","ln":7},{"s":19,"a":5,"wi":9,"t":"فَهَبْ","n":"فهب","ln":7},{"s":19,"a":5,"wi":10,"t":"لِى","n":"لي","ln":7},{"s":19,"a":5,"wi":11,"t":"مِن","n":"من","ln":7},{"s":19,"a":5,"wi":12,"t":"لَّدُنكَ","n":"لدنك","ln":7},{"s":19,"a":5,"wi":13,"t":"وَلِيًّۭا","n":"وليا","ln":7},{"s":19,"a":6,"wi":1,"t":"يَرِثُنِى","n":"يرثني","ln":7},{"s":19,"a":6,"wi":2,"t":"وَيَرِثُ","n":"ويرث","ln":7},{"s":19,"a":6,"wi":3,"t":"مِنْ","n":"من","ln":8},{"s":19,"a":6,"wi":4,"t":"ءَالِ","n":"ءال","ln":8},{"s":19,"a":6,"wi":5,"t":"يَعْقُوبَ ۖ","n":"يعقوب","ln":8},{"s":19,"a":6,"wi":6,"t":"وَٱجْعَلْهُ","n":"واجعله","ln":8},{"s":19,"a":6,"wi":7,"t":"رَبِّ","n":"رب","ln":8},{"s":19,"a":6,"wi":8,"t":"رَضِيًّۭا","n":"رضيا","ln":8},{"s":19,"a":7,"wi":1,"t":"يَـٰزَكَرِيَّآ","n":"يـزكريا","ln":8},{"s":19,"a":7,"wi":2,"t":"إِنَّا","n":"انا","ln":9},{"s":19,"a":7,"wi":3,"t":"نُبَشِّرُكَ","n":"نبشرك","ln":9},{"s":19,"a":7,"wi":4,"t":"بِغُلَـٰمٍ","n":"بغلـم","ln":9},{"s":19,"a":7,"wi":5,"t":"ٱسْمُهُۥ","n":"اسمه","ln":9},{"s":19,"a":7,"wi":6,"t":"يَحْيَىٰ","n":"يحيي","ln":9},{"s":19,"a":7,"wi":7,"t":"لَمْ","n":"لم","ln":9},{"s":19,"a":7,"wi":8,"t":"نَجْعَل","n":"نجعل","ln":9},{"s":19,"a":7,"wi":9,"t":"لَّهُۥ","n":"له","ln":9},{"s":19,"a":7,"wi":10,"t":"مِن","n":"من","ln":9},{"s":19,"a":7,"wi":11,"t":"قَبْلُ","n":"قبل","ln":9},{"s":19,"a":7,"wi":12,"t":"سَمِيًّۭا","n":"سميا","ln":9},{"s":19,"a":8,"wi":1,"t":"قَالَ","n":"قال","ln":10},{"s":19,"a":8,"wi":2,"t":"رَبِّ","n":"رب","ln":10},{"s":19,"a":8,"wi":3,"t":"أَنَّىٰ","n":"اني","ln":10},{"s":19,"a":8,"wi":4,"t":"يَكُونُ","n":"يكون","ln":10},{"s":19,"a":8,"wi":5,"t":"لِى","n":"لي","ln":10},{"s":19,"a":8,"wi":6,"t":"غُلَـٰمٌۭ","n":"غلـم","ln":10},{"s":19,"a":8,"wi":7,"t":"وَكَانَتِ","n":"وكانت","ln":10},{"s":19,"a":8,"wi":8,"t":"ٱمْرَأَتِى","n":"امراتي","ln":10},{"s":19,"a":8,"wi":9,"t":"عَاقِرًۭا","n":"عاقرا","ln":11},{"s":19,"a":8,"wi":10,"t":"وَقَدْ","n":"وقد","ln":11},{"s":19,"a":8,"wi":11,"t":"بَلَغْتُ","n":"بلغت","ln":11},{"s":19,"a":8,"wi":12,"t":"مِنَ","n":"من","ln":11},{"s":19,"a":8,"wi":13,"t":"ٱلْكِبَرِ","n":"الكبر","ln":11},{"s":19,"a":8,"wi":14,"t":"عِتِيًّۭا","n":"عتيا","ln":11},{"s":19,"a":9,"wi":1,"t":"قَالَ","n":"قال","ln":11},{"s":19,"a":9,"wi":2,"t":"كَذَٰلِكَ","n":"كذلك","ln":11},{"s":19,"a":9,"wi":3,"t":"قَالَ","n":"قال","ln":12},{"s":19,"a":9,"wi":4,"t":"رَبُّكَ","n":"ربك","ln":12},{"s":19,"a":9,"wi":5,"t":"هُوَ","n":"هو","ln":12},{"s":19,"a":9,"wi":6,"t":"عَلَىَّ","n":"علي","ln":12},{"s":19,"a":9,"wi":7,"t":"هَيِّنٌۭ","n":"هين","ln":12},{"s":19,"a":9,"wi":8,"t":"وَقَدْ","n":"وقد","ln":12},{"s":19,"a":9,"wi":9,"t":"خَلَقْتُكَ","n":"خلقتك","ln":12},{"s":19,"a":9,"wi":10,"t":"مِن","n":"من","ln":12},{"s":19,"a":9,"wi":11,"t":"قَبْلُ","n":"قبل","ln":12},{"s":19,"a":9,"wi":12,"t":"وَلَمْ","n":"ولم","ln":12},{"s":19,"a":9,"wi":13,"t":"تَكُ","n":"تك","ln":12},{"s":19,"a":9,"wi":14,"t":"شَيْـًۭٔا","n":"شيـا","ln":13},{"s":19,"a":10,"wi":1,"t":"قَالَ","n":"قال","ln":13},{"s":19,"a":10,"wi":2,"t":"رَبِّ","n":"رب","ln":13},{"s":19,"a":10,"wi":3,"t":"ٱجْعَل","n":"اجعل","ln":13},{"s":19,"a":10,"wi":4,"t":"لِّىٓ","n":"لي","ln":13},{"s":19,"a":10,"wi":5,"t":"ءَايَةًۭ ۚ","n":"ءايه","ln":13},{"s":19,"a":10,"wi":6,"t":"قَالَ","n":"قال","ln":13},{"s":19,"a":10,"wi":7,"t":"ءَايَتُكَ","n":"ءايتك","ln":13},{"s":19,"a":10,"wi":8,"t":"أَلَّا","n":"الا","ln":13},{"s":19,"a":10,"wi":9,"t":"تُكَلِّمَ","n":"تكلم","ln":14},{"s":19,"a":10,"wi":10,"t":"ٱلنَّاسَ","n":"الناس","ln":14},{"s":19,"a":10,"wi":11,"t":"ثَلَـٰثَ","n":"ثلـث","ln":14},{"s":19,"a":10,"wi":12,"t":"لَيَالٍۢ","n":"ليال","ln":14},{"s":19,"a":10,"wi":13,"t":"سَوِيًّۭا","n":"سويا","ln":14},{"s":19,"a":11,"wi":1,"t":"فَخَرَجَ","n":"فخرج","ln":14},{"s":19,"a":11,"wi":2,"t":"عَلَىٰ","n":"علي","ln":14},{"s":19,"a":11,"wi":3,"t":"قَوْمِهِۦ","n":"قومه","ln":14},{"s":19,"a":11,"wi":4,"t":"مِنَ","n":"من","ln":15},{"s":19,"a":11,"wi":5,"t":"ٱلْمِحْرَابِ","n":"المحراب","ln":15},{"s":19,"a":11,"wi":6,"t":"فَأَوْحَىٰٓ","n":"فاوحي","ln":15},{"s":19,"a":11,"wi":7,"t":"إِلَيْهِمْ","n":"اليهم","ln":15},{"s":19,"a":11,"wi":8,"t":"أَن","n":"ان","ln":15},{"s":19,"a":11,"wi":9,"t":"سَبِّحُوا۟","n":"سبحوا","ln":15},{"s":19,"a":11,"wi":10,"t":"بُكْرَةًۭ","n":"بكره","ln":15},{"s":19,"a":11,"wi":11,"t":"وَعَشِيًّۭا","n":"وعشيا","ln":15}]